{
  "A4 Paper": "printing",
  "Address Sticker": "printing",
  "AMD Letterhead": "printing",
  "AMD Continue Sheet": "printing",
  "ASSPL Letterhead": "printing",
  "ASSPL Continue Sheet": "printing",
  "ATS Letterhead": "printing",
  "AA battery": "stationery",
  "AAA battery": "stationery",
  "Bell pins": "stationery",
  "Binder clips 19mm": "stationery",
  "Binder clips 25mm": "stationery",
  "Binding Tag": "stationery",
  "Blue Pen": "stationery",
  "Board Marker black": "stationery",
  "Board Marker Blue": "stationery",
  "Box File": "stationery",
  "Button File": "stationery",
  "Cable tag": "stationery",
  "Calculator": "stationery",
  "CD marker": "stationery",
  "Cloth Cover A3": "stationery",
  "Cloth Cover A4": "stationery",
  "Colin": "stationery",
  "Cutter small": "stationery",
  "Cutter blade small": "stationery",
  "Corbon paper": "stationery",
  "Cutter blade Big": "stationery",
  "Cutter big": "stationery",
  "Drawning Pin": "stationery",
  "Eraser": "stationery",
  "Fevi Stick": "stationery",
  "Flat file": "stationery",
  "Green paper (A4 size)": "stationery",
  "Highlighter green": "stationery",
  "Highlighter Pink": "stationery",
  "Highlighter yellow": "stationery",
  "L-folder": "stationery",
  "Paper clips big": "stationery",
  "Paper clips Small": "stationery",
  "Paper punching": "stationery",
  "Pencil": "stationery",
  "Permanent Marker": "stationery",
  "Petty cash book AMD": "stationery",
  "Petty cash book ASSPL": "stationery",
  "Punch Folder": "stationery",
  "Red File Tag": "stationery",
  "Red Pen": "stationery",
  "Room Spray": "stationery",
  "Rubber band": "stationery",
  "Rule Note": "stationery",
  "Ruler": "stationery",
  "scissors": "stationery",
  "Sharpner": "stationery",
  "Stapler": "stationery",
  "Stapler pin big": "stationery",
  "stapler pin remover": "stationery",
  "Stapler pin small": "stationery",
  "Stick File": "stationery",
  "Sticky notes": "stationery",
  "Tapes 1Inch White": "stationery",
  "Tapes 2Inch Brown": "stationery",
  "White Envelope big": "stationery",
  "White Envelope check type": "stationery",
  "White Envelope Small": "stationery",
  "Whitner": "stationery",
  "HIGHLIGHTER ORANGE": "stationery",
  "Gel Pen Black": "stationery",
  "Other": "stationery"
}